pyposast/__init__.py
pyposast/constants.py
pyposast/cross_version.py
pyposast/node_helpers.py
pyposast/parser.py
pyposast/utils.py
pyposast/visitor.py
PyPosAST-1.6.2.dist-info/LICENSE
PyPosAST-1.6.2.dist-info/METADATA
PyPosAST-1.6.2.dist-info/WHEEL
PyPosAST-1.6.2.dist-info/top_level.txt
PyPosAST-1.6.2.dist-info/RECORD
