Metadata-Version: 2.1
Name: PyPosAST
Version: 1.6.2
Summary: Extends Python ast nodes with positional informations
Author-email: João Felipe Pimentel <joaofelipenp@gmail.com>
License: MIT License
Project-URL: Homepage, https://github.com/JoaoFelipe/PyPosAST
Project-URL: Repository, https://github.com/JoaoFelipe/PyPosAST.git
Project-URL: Issues, https://github.com/JoaoFelipe/PyPosAST/issues
Keywords: ast,python,position,offset
Classifier: Development Status :: 5 - Production/Stable
Classifier: Intended Audience :: Developers
Classifier: Topic :: Software Development :: Compilers
Classifier: Topic :: Software Development :: Interpreters
Classifier: Topic :: Software Development :: Pre-processors
Classifier: License :: OSI Approved :: MIT License
Classifier: Programming Language :: Python :: 2.7
Classifier: Programming Language :: Python :: 3
Classifier: Programming Language :: Python :: 3.6
Classifier: Programming Language :: Python :: 3.7
Classifier: Programming Language :: Python :: 3.8
Classifier: Programming Language :: Python :: 3.9
Classifier: Programming Language :: Python :: 3.10
Classifier: Programming Language :: Python :: 3.11
Classifier: Programming Language :: Python :: 3.12
Classifier: Programming Language :: Python :: 3.13
License-File: LICENSE
